.coveragerc
.travis.yml
AUTHORS.rst
CHANGELOG.rst
CONTRIBUTING.rst
LICENSE
MANIFEST.in
README.rst
appveyor.yml
setup.cfg
setup.py
tox.ini
ci/appveyor-bootstrap.ps1
ci/appveyor-with-compiler.cmd
ci/bootstrap.py
ci/templates/.travis.yml
ci/templates/appveyor.yml
ci/templates/tox.ini
docs/authors.rst
docs/changelog.rst
docs/conf.py
docs/contributing.rst
docs/index.rst
docs/installation.rst
docs/readme.rst
docs/requirements.txt
docs/spelling_wordlist.txt
docs/usage.rst
docs/reference/index.rst
docs/reference/pip2amch.rst
src/pip2amch/__init__.py
src/pip2amch/__main__.py
src/pip2amch.egg-info/PKG-INFO
src/pip2amch.egg-info/SOURCES.txt
src/pip2amch.egg-info/dependency_links.txt
src/pip2amch.egg-info/entry_points.txt
src/pip2amch.egg-info/not-zip-safe
src/pip2amch.egg-info/requires.txt
src/pip2amch.egg-info/top_level.txt
tests/test_pip2amch.py