Metadata-Version: 1.1
Name: pip2amch
Version: 0.1.0
Summary: Command to transform pip's requirements.txt into a csv for batch upload to https://allmychanges.com
Home-page: https://github.com/allmychanges/pip2amch
Author: Alexander Artemenko
Author-email: svetlyak.40wt@gmail.com
License: BSD
Keywords: allmychanges,release notes,amch,changelog,pip,requirements
Platform: UNKNOWN
Classifier: Development Status :: 4 - Beta
Classifier: Intended Audience :: Developers
Classifier: License :: OSI Approved :: BSD License
Classifier: Environment :: Console
Classifier: Operating System :: Unix
Classifier: Operating System :: POSIX
Classifier: Operating System :: Microsoft :: Windows
Classifier: Programming Language :: Python
Classifier: Programming Language :: Python :: 2.6
Classifier: Programming Language :: Python :: 2.7
Classifier: Programming Language :: Python :: 3
Classifier: Programming Language :: Python :: 3.3
Classifier: Programming Language :: Python :: 3.4
Classifier: Programming Language :: Python :: Implementation :: CPython
Classifier: Programming Language :: Python :: Implementation :: PyPy
Classifier: Topic :: Utilities
